mediascope_api/__init__.py
mediascope_api/core/__init__.py
mediascope_api/core/cache.py
mediascope_api/core/errors.py
mediascope_api/core/net.py
mediascope_api/core/sql.py
mediascope_api/core/tasks.py
mediascope_api/core/utils.py
mediascope_api/counter/__init__.py
mediascope_api/counter/catalogs.py
mediascope_api/counter/tasks.py
mediascope_api/crossweb/__init__.py
mediascope_api/crossweb/catalogs.py
mediascope_api/crossweb/checks.py
mediascope_api/crossweb/tasks.py
mediascope_api/mediavortex/__init__.py
mediascope_api/mediavortex/catalogs.py
mediascope_api/mediavortex/checks.py
mediascope_api/mediavortex/tasks.py
mediascope_api/responsum/__init__.py
mediascope_api/responsum/catalogs.py
mediascope_api/responsum/tasks.py
mediascope_api_lib-1.6.3.dist-info/LICENSE
mediascope_api_lib-1.6.3.dist-info/METADATA
mediascope_api_lib-1.6.3.dist-info/WHEEL
mediascope_api_lib-1.6.3.dist-info/top_level.txt
mediascope_api_lib-1.6.3.dist-info/RECORD
