Metadata-Version: 2.1
Name: mediascope-api-lib
Version: 1.6.3
Summary: Library for work with the Mediascope-Delivery-API
Home-page: https://github.com/MEDIASCOPE-JSC/mediascope-api-lib
Author: Sergey Poterianski
Author-email: sergey.poterianski@mediascope.net
Maintainer: Mediascope JSC
Maintainer-email: github@mediascope.net
License: BSD-3-Clause
Download-URL: https://github.com/MEDIASCOPE-JSC/mediascope-api-lib/tarball/v1.6.3
Platform: UNKNOWN
Classifier: Development Status :: 5 - Production/Stable
Classifier: Programming Language :: Python :: 3.6
Classifier: Natural Language :: Russian
Classifier: License :: OSI Approved :: BSD License
Classifier: Operating System :: Microsoft :: Windows
Classifier: Operating System :: POSIX
Classifier: Operating System :: Unix
Classifier: Operating System :: MacOS
Requires: pandas
Requires: requests
Requires: pyparsing
Requires: urllib3
Requires-Python: >=3.6
License-File: LICENSE
Requires-Dist: pandas
Requires-Dist: requests
Requires-Dist: pyparsing
Requires-Dist: urllib3 (>=1.26.7)
